portus/__init__.py
portus/api.py
portus/agents/__init__.py
portus/agents/base.py
portus/agents/lighthouse/__init__.py
portus/agents/lighthouse/agent.py
portus/agents/lighthouse/graph.py
portus/agents/lighthouse/system_prompt.jinja
portus/agents/lighthouse/utils.py
portus/agents/react_duckdb/__init__.py
portus/agents/react_duckdb/agent.py
portus/caches/__init__.py
portus/caches/in_mem_cache.py
portus/configs/__init__.py
portus/configs/llm.py
portus/core/__init__.py
portus/core/cache.py
portus/core/executor.py
portus/core/opa.py
portus/core/pipe.py
portus/core/session.py
portus/core/visualizer.py
portus/duckdb/__init__.py
portus/duckdb/react_tools.py
portus/duckdb/utils.py
portus/visualizers/__init__.py
portus/visualizers/dumb.py
portus/visualizers/vega_chat.py
portus_ai-0.0.4.dist-info/METADATA
portus_ai-0.0.4.dist-info/WHEEL
portus_ai-0.0.4.dist-info/RECORD
