Metadata-Version: 2.4
Name: portus-ai
Version: 0.0.4
Summary: Portus: NL queries for data
Classifier: Operating System :: OS Independent
Classifier: Programming Language :: Python :: 3
Requires-Python: >=3.12
Requires-Dist: duckdb>=1.3.0
Requires-Dist: edaplot-vl~=0.0.3
Requires-Dist: jinja2>=3.1.6
Requires-Dist: langchain-anthropic<0.4,>=0.3.10
Requires-Dist: langchain-ollama>=0.3.10
Requires-Dist: langchain-openai<0.4,>=0.3.8
Requires-Dist: langchain<0.4,>=0.3.20
Requires-Dist: langgraph>=0.6.8
Requires-Dist: matplotlib>=3.10.0
Requires-Dist: pandas>=2.2.2
Requires-Dist: psycopg2-binary>=2.9.10
Requires-Dist: pydantic<3,>=2.8.0
Requires-Dist: tabulate>=0.9.0
Provides-Extra: examples
Requires-Dist: notebook>=7.4.7; extra == 'examples'
Requires-Dist: python-dotenv>=1.1.1; extra == 'examples'
